{"Stats_Extension_Index":[

	{"Name":"STATS-APRIORI",
	 "Plugins":"R",
	 "Product_Minimum_Version_List":["18","23"],
	 "Extension_Version_List":[	 
		 { "18":
		   {"Extension_Version":"1.0.4",
		    "Download_Link":"https://github.com/IBMPredictiveAnalytics/STATS-APRIORI/archive/v1.0.4.zip",
		    "Product_Maximum_Version":"22" } },

		 { "23":
		   {"Extension_Version":"1.0.5",
		    "Download_Link":"https://github.com/IBMPredictiveAnalytics/STATS-APRIORI/archive/v1.0.5.zip",
		    "Product_Maximum_Version":"" } } ]
	}

 ]

}
